glia/.gitignore
glia/__init__.py
glia/_cli.py
glia/_fs.py
glia/_glia.py
glia/_hash.py
glia/_local.py
glia/_mpi.py
glia/assets.py
glia/exceptions.py
glia/library.py
glia/neuron.py
glia/resolution.py
glia/packaging/__init__.py
glia/packaging/_ast.py
glia/packaging/cookiecutter-glia/.gitignore
glia/packaging/cookiecutter-glia/README.rst
glia/packaging/cookiecutter-glia/cookiecutter.json
glia/packaging/cookiecutter-glia/hooks/pre_gen_project.py
glia/packaging/cookiecutter-glia/{{cookiecutter.project_slug}}/LICENSE
glia/packaging/cookiecutter-glia/{{cookiecutter.project_slug}}/README.rst
glia/packaging/cookiecutter-glia/{{cookiecutter.project_slug}}/pyproject.toml
glia/packaging/cookiecutter-glia/{{cookiecutter.project_slug}}/{{cookiecutter.project_slug}}/__init__.py
glia/packaging/cookiecutter-glia/{{cookiecutter.project_slug}}/{{cookiecutter.project_slug}}/mods/.gitkeep
nmodl_glia-7.2.1.dist-info/entry_points.txt
nmodl_glia-7.2.1.dist-info/licenses/LICENSE
nmodl_glia-7.2.1.dist-info/WHEEL
nmodl_glia-7.2.1.dist-info/METADATA
nmodl_glia-7.2.1.dist-info/RECORD
