Metadata-Version: 2.4
Name: nmodl-glia
Version: 7.2.1
Summary: NMODL Asset Manager for Arbor and NEURON.
Author-email: Robin De Schepper <robin@alexandria.sc>
Requires-Python: >=3.10,<4
Classifier: License :: OSI Approved :: GNU General Public License v3 or later (GPLv3+)
License-File: LICENSE
Requires-Dist: click~=8.0
Requires-Dist: appdirs~=1.0
Requires-Dist: errr~=1.2
Requires-Dist: cookiecutter~=2.0
Requires-Dist: black>=24.0
Requires-Dist: toml~=0.10
Requires-Dist: packaging~=24.0
Requires-Dist: NEURON>=9.0; sys_platform != 'win32'
Requires-Dist: importlib_metadata~=6.5
Requires-Dist: arbor~=0.10 ; extra == "arbor"
Requires-Dist: nrn-patch~=7.0 ; extra == "neuron"
Requires-Dist: mpi4py~=3.0 ; extra == "parallel"
Provides-Extra: arbor
Provides-Extra: neuron
Provides-Extra: parallel
